AUTHORS
LICENSE
MANIFEST.in
README.rst
setup.py
django_email_templates.egg-info/PKG-INFO
django_email_templates.egg-info/SOURCES.txt
django_email_templates.egg-info/dependency_links.txt
django_email_templates.egg-info/top_level.txt
email_templates/__init__.py